chima_rufus/__init__.py
chima_rufus/agent.py
chima_rufus/api.py
chima_rufus/crawler.py
chima_rufus/extractor.py
chima_rufus/logger.py
chima_rufus-0.2.dist-info/METADATA
chima_rufus-0.2.dist-info/WHEEL
chima_rufus-0.2.dist-info/entry_points.txt
chima_rufus-0.2.dist-info/top_level.txt
chima_rufus-0.2.dist-info/RECORD
