Metadata-Version: 2.2
Name: chima_rufus
Version: 0.2
Author: Mukesh Kumar Javvaji
Author-email: mukeshjavvaji123@gmail.com
Requires-Dist: annotated-types==0.7.0
Requires-Dist: anyio==4.8.0
Requires-Dist: attrs==25.2.0
Requires-Dist: beautifulsoup4==4.13.3
Requires-Dist: blis==1.2.0
Requires-Dist: bs4==0.0.2
Requires-Dist: catalogue==2.0.10
Requires-Dist: certifi==2025.1.31
Requires-Dist: charset-normalizer==3.4.1
Requires-Dist: click==8.1.8
Requires-Dist: cloudpathlib==0.21.0
Requires-Dist: confection==0.1.5
Requires-Dist: cymem==2.0.11
Requires-Dist: fastapi==0.115.11
Requires-Dist: h11==0.14.0
Requires-Dist: idna==3.10
Requires-Dist: Jinja2==3.1.6
Requires-Dist: joblib==1.4.2
Requires-Dist: langcodes==3.5.0
Requires-Dist: language_data==1.3.0
Requires-Dist: marisa-trie==1.2.1
Requires-Dist: markdown-it-py==3.0.0
Requires-Dist: MarkupSafe==3.0.2
Requires-Dist: mdurl==0.1.2
Requires-Dist: murmurhash==1.0.12
Requires-Dist: nltk==3.9.1
Requires-Dist: numpy==2.2.3
Requires-Dist: outcome==1.3.0.post0
Requires-Dist: packaging==24.2
Requires-Dist: preshed==3.0.9
Requires-Dist: pydantic==2.10.6
Requires-Dist: pydantic_core==2.27.2
Requires-Dist: Pygments==2.19.1
Requires-Dist: PySocks==1.7.1
Requires-Dist: python-dotenv==1.0.1
Requires-Dist: requests==2.32.3
Requires-Dist: rich==13.9.4
Requires-Dist: scikit-learn==1.6.1
Requires-Dist: scipy==1.15.2
Requires-Dist: selenium==4.29.0
Requires-Dist: setuptools==76.0.0
Requires-Dist: shellingham==1.5.4
Requires-Dist: smart-open==7.1.0
Requires-Dist: sniffio==1.3.1
Requires-Dist: sortedcontainers==2.4.0
Requires-Dist: soupsieve==2.6
Requires-Dist: spacy==3.8.4
Requires-Dist: spacy-legacy==3.0.12
Requires-Dist: spacy-loggers==1.0.5
Requires-Dist: srsly==2.5.1
Requires-Dist: starlette==0.46.1
Requires-Dist: thinc==8.3.4
Requires-Dist: threadpoolctl==3.5.0
Requires-Dist: tqdm==4.67.1
Requires-Dist: trio==0.29.0
Requires-Dist: trio-websocket==0.12.2
Requires-Dist: typer==0.15.2
Requires-Dist: typing_extensions==4.12.2
Requires-Dist: urllib3==2.3.0
Requires-Dist: uvicorn==0.34.0
Requires-Dist: wasabi==1.1.3
Requires-Dist: weasel==0.4.1
Requires-Dist: webdriver-manager==4.0.2
Requires-Dist: websocket-client==1.8.0
Requires-Dist: wrapt==1.17.2
Requires-Dist: wsproto==1.2.0
Dynamic: author
Dynamic: author-email
Dynamic: requires-dist
